buttonizer/__init__.py
buttonizer/config.py
buttonizer/config.yaml
buttonizer/main.py
buttonizer-1.0.0.dist-info/METADATA
buttonizer-1.0.0.dist-info/WHEEL
buttonizer-1.0.0.dist-info/top_level.txt
buttonizer-1.0.0.dist-info/RECORD
